xbrl_us/__init__.py
xbrl_us/__main__.py
xbrl_us/app.py
xbrl_us/cli.py
xbrl_us/xbrl_us.py
xbrl_us/.streamlit/config.toml
xbrl_us/meta_endpoints/assertion.yml
xbrl_us/meta_endpoints/concept.yml
xbrl_us/meta_endpoints/cube.yml
xbrl_us/meta_endpoints/document.yml
xbrl_us/meta_endpoints/dts.yml
xbrl_us/meta_endpoints/entity report.yml
xbrl_us/meta_endpoints/entity.yml
xbrl_us/meta_endpoints/fact.yml
xbrl_us/meta_endpoints/label.yml
xbrl_us/meta_endpoints/network relationship.yml
xbrl_us/meta_endpoints/relationship.yml
xbrl_us/meta_endpoints/report fact.yml
xbrl_us/meta_endpoints/report network.yml
xbrl_us/meta_endpoints/report.yml
xbrl_us/utils/__init__.py
xbrl_us/utils/crypto.py
xbrl_us/utils/exceptions.py
xbrl_us/utils/generator.py
xbrl_us/xtypes/__init__.py
xbrl_us/xtypes/endpoints.py
xbrl_us/xtypes/types.py
xbrl_us-1.0.1.dist-info/licenses/LICENSE
xbrl_us-1.0.1.dist-info/METADATA
xbrl_us-1.0.1.dist-info/WHEEL
xbrl_us-1.0.1.dist-info/entry_points.txt
xbrl_us-1.0.1.dist-info/top_level.txt
xbrl_us-1.0.1.dist-info/RECORD
