Metadata-Version: 2.4
Name: xbrl-us
Version: 1.0.1
Summary: Python wrapper for xbrl.us API
Home-page: https://github.com/hamid-vakilzadeh/python-xbrl-us
Author: hamid-vakilzadeh
Author-email: vakilzas@uww.edu
License: MIT
Project-URL: Documentation, https://python-xbrl-us.readthedocs.io/
Project-URL: Changelog, https://python-xbrl-us.readthedocs.io/en/latest/changelog.html
Project-URL: Issue Tracker, https://github.com/hamid-vakilzadeh/python-xbrl-us/issues
Classifier: Development Status :: 2 - Pre-Alpha
Classifier: Intended Audience :: Developers
Classifier: License :: OSI Approved :: MIT License
Classifier: Operating System :: Unix
Classifier: Operating System :: POSIX
Classifier: Operating System :: Microsoft :: Windows
Classifier: Programming Language :: Python
Classifier: Programming Language :: Python :: 3
Classifier: Programming Language :: Python :: 3 :: Only
Classifier: Programming Language :: Python :: 3.9
Classifier: Programming Language :: Python :: 3.10
Classifier: Programming Language :: Python :: 3.11
Classifier: Programming Language :: Python :: 3.12
Classifier: Programming Language :: Python :: 3.13
Classifier: Programming Language :: Python :: Implementation :: CPython
Classifier: Programming Language :: Python :: Implementation :: PyPy
Classifier: Topic :: Utilities
Requires-Python: >=3.9
License-File: LICENSE
Requires-Dist: requests<3,>=2.25.1
Requires-Dist: pandas<3,>=1.3.0
Requires-Dist: PyYAML<7,>=5.3
Requires-Dist: streamlit<2,>=1.44.1
Requires-Dist: retry<1,>=0.9.2
Requires-Dist: tqdm<5,>=4.61.2
Requires-Dist: stqdm<1,>=0.0.5
Requires-Dist: aiohttp<4,>=3.8.4
Requires-Dist: nest-asyncio<2,>=1.5.6
Requires-Dist: cryptography<45,>=44.0.2
Provides-Extra: arrow
Requires-Dist: pyarrow<13.0.0,>=10.0.0; extra == "arrow"
Provides-Extra: complete
Requires-Dist: pyarrow<13.0.0,>=10.0.0; extra == "complete"
Dynamic: author
Dynamic: author-email
Dynamic: classifier
Dynamic: description
Dynamic: description-content-type
Dynamic: home-page
Dynamic: license
Dynamic: license-file
Dynamic: project-url
Dynamic: provides-extra
Dynamic: requires-dist
Dynamic: requires-python
Dynamic: summary
